pyw2v2/__init__.py
pyw2v2/components/__init__.py
pyw2v2/components/dataset_proc.py
pyw2v2/components/metrics.py
pyw2v2/components/model_ctc.py
pyw2v2/components/external/__init__.py
pyw2v2/components/external/data_collator_ctc.py
pyw2v2/utils/__init__.py
pyw2v2/utils/utils.py
pyw2v2-0.0.2.dist-info/LICENSE.txt
pyw2v2-0.0.2.dist-info/METADATA
pyw2v2-0.0.2.dist-info/WHEEL
pyw2v2-0.0.2.dist-info/top_level.txt
pyw2v2-0.0.2.dist-info/RECORD
